omni/asset_validator/__init__.py
omni/asset_validator/__main__.py
omni/asset_validator/_assets.py
omni/asset_validator/_atomic_asset_checker.py
omni/asset_validator/_base_rule_checker.py
omni/asset_validator/_base_rule_metadata.py
omni/asset_validator/_base_rules.py
omni/asset_validator/_capabilities.py
omni/asset_validator/_categories.py
omni/asset_validator/_cli.py
omni/asset_validator/_compliance_checker.py
omni/asset_validator/_compliance_runners.py
omni/asset_validator/_context_managers.py
omni/asset_validator/_csv_reports.py
omni/asset_validator/_default_categories.py
omni/asset_validator/_deprecate.py
omni/asset_validator/_docs.py
omni/asset_validator/_engine.py
omni/asset_validator/_events.py
omni/asset_validator/_examples.py
omni/asset_validator/_expression.py
omni/asset_validator/_features.py
omni/asset_validator/_fix.py
omni/asset_validator/_geometry_checker.py
omni/asset_validator/_graph_tools.py
omni/asset_validator/_identifiers.py
omni/asset_validator/_import_utils.py
omni/asset_validator/_issues.py
omni/asset_validator/_json_reports.py
omni/asset_validator/_layer_checker.py
omni/asset_validator/_layout_checker.py
omni/asset_validator/_material_checker.py
omni/asset_validator/_mesh_tools.py
omni/asset_validator/_misc_checker.py
omni/asset_validator/_omni_utils.py
omni/asset_validator/_parameters.py
omni/asset_validator/_performance_checker.py
omni/asset_validator/_physics_checker.py
omni/asset_validator/_profiles.py
omni/asset_validator/_registry.py
omni/asset_validator/_requirements.py
omni/asset_validator/_results.py
omni/asset_validator/_semver.py
omni/asset_validator/_stats.py
omni/asset_validator/_url_utils.py
omni/asset_validator/_usd_utils.py
omni/asset_validator/_usd_validator_adapter.py
omni/asset_validator/_utf8_checker.py
omni/asset_validator/_version.py
omni/asset_validator/tests/__init__.py
omni/asset_validator/tests/_assertions.py
omni/asset_validator/tests/_testcases.py
omni/capabilities/__init__.py
omni/capabilities/_capabilities.py
omniverse_asset_validator-1.9.2.dist-info/METADATA
omniverse_asset_validator-1.9.2.dist-info/WHEEL
omniverse_asset_validator-1.9.2.dist-info/entry_points.txt
omniverse_asset_validator-1.9.2.dist-info/RECORD
