Metadata-Version: 2.4
Name: omniverse-asset-validator
Version: 1.9.2
Summary: NVIDIA Asset Validator
License-Expression: Apache-2.0
Author: NVIDIA
Requires-Python: >=3.10,<3.13
Classifier: Programming Language :: Python :: 3
Classifier: Programming Language :: Python :: 3.10
Classifier: Programming Language :: Python :: 3.11
Classifier: Programming Language :: Python :: 3.12
Provides-Extra: numpy
Provides-Extra: usd
Requires-Dist: numpy (>=1,<2) ; extra == "numpy"
Requires-Dist: usd-core (>=22.11) ; extra == "usd"
Project-URL: Documentation, https://docs.omniverse.nvidia.com/kit/docs/asset-validator
Project-URL: Homepage, https://docs.omniverse.nvidia.com/kit/docs/asset-validator
